README.md
setup.py
aprsjson/__init__.py
aprsjson/base91.py
aprsjson/common.py
aprsjson/exceptions.py
aprsjson/message.py
aprsjson/position.py
aprsjson/weather.py
aprsjson.egg-info/PKG-INFO
aprsjson.egg-info/SOURCES.txt
aprsjson.egg-info/dependency_links.txt
aprsjson.egg-info/requires.txt
aprsjson.egg-info/top_level.txt