Metadata-Version: 1.0
Name: aprsjson
Version: 1.0
Summary: Module for parsing APRS packet as JSON
Home-page: https://github.com/josefmtd/aprs-json
Author: Josef Matondang
Author-email: admin@josefmtd.com
License: UNKNOWN
Platform: UNKNOWN
